<nav>

    <!-- Prepare Phase -->
    <node displaytext="Prepare" id="phase-prepare">
        <node displaytext="Assessment Configuration" id="info1" path="assessment/{:id}/prepare/info1" />
        <node displaytext="Assessment Information" id="info2" path="assessment/{:id}/prepare/info2" />

        <!-- model select (this will be going away when the Gallery Interface is ready) -->
        <node displaytext="Model Select" id="model-select" path="assessment/{:id}/prepare/model-select" />


        <!-- maturity model tutorials -->
        <node displaytext="CMMC Tutorial" id="tutorial-cmmc" path="assessment/{:id}/prepare/tutorial-cmmc" visible="MATURITY:CMMC" />
        <node displaytext="CMMC Target Level Selection" id="cmmc-levels" path="assessment/{:id}/prepare/cmmc-levels" visible="MATURITY-ANY(CMMC,CMMC2)" />

        <node displaytext="CMMC Tutorial" id="tutorial-cmmc2" path="assessment/{:id}/prepare/tutorial-cmmc2" visible="MATURITY:CMMC2" />

        <node displaytext="EDM Tutorial" id="tutorial-edm" path="assessment/{:id}/prepare/tutorial-edm" visible="MATURITY:EDM" />

        <node displaytext="CRR Tutorial" id="tutorial-crr" path="assessment/{:id}/prepare/tutorial-crr" visible="MATURITY:CRR" />

        <node displaytext="Ransomware Readiness Tutorial" id="tutorial-rra" path="assessment/{:id}/prepare/tutorial-rra" visible="MATURITY:RRA" />

        <node displaytext="CIS Tutorial" id="tutorial-cis" path="assessment/{:id}/prepare/tutorial-cis" visible="MATURITY:CIS" />
        <node displaytext="CIS Configuration" id="config-cis" path="assessment/{:id}/prepare/config-cis" visible="MATURITY:CIS" />
        <node displaytext="Critical Service Information" id="csi" path="assessment/{:id}/prepare/csi" visible="MATURITY:CIS" />




        <!-- ACET-specific screens -->
        <node displaytext="Inherent Risk Profiles" id="irp" path="assessment/{:id}/prepare/irp" visible="MATURITY:ACET" />
        <node displaytext="Inherent Risk Profile Summary" id="irp-summary" path="assessment/{:id}/prepare/irp-summary" visible="MATURITY:ACET" />

    </node>



    <!-- Assessment Phase -->
    <node displaytext="Assessment" id="phase-assessment">

        <node displaytext="Maturity Questions" id="maturity-questions" path="assessment/{:id}/maturity-questions" visible="MATURITY-NOT:CIS MATURITY-NOT:ACET" />


        <node displaytext="CIS Questions" visible="MATURITY:CIS">
            <node id="maturity-questions-nested-2301" displaytext="Cybersecurity Management">
                <node id="maturity-questions-nested-2306" path="assessment/{:id}/maturity-questions-nested/2306" displaytext="1. Cybersecurity Leadership" />
                <node id="maturity-questions-nested-2307" displaytext="Cybersecurity Architecture">
                    <node id="maturity-questions-nested-2328" path="assessment/{:id}/maturity-questions-nested/2328" displaytext="2. Inventory" />
                    <node id="maturity-questions-nested-2329" path="assessment/{:id}/maturity-questions-nested/2329" displaytext="3. System Architecture" />
                    <node id="maturity-questions-nested-2330" path="assessment/{:id}/maturity-questions-nested/2330" displaytext="4. Security Architecture" />
                </node>
                <node id="maturity-questions-nested-2308" path="assessment/{:id}/maturity-questions-nested/2308" displaytext="5. Change Management" />
                <node id="maturity-questions-nested-2309" path="assessment/{:id}/maturity-questions-nested/2309" displaytext="6. Lifecycle Tracking" />
                <node id="maturity-questions-nested-2310" path="assessment/{:id}/maturity-questions-nested/2310" displaytext="7. Assessment and Evaluations" />
                <node id="maturity-questions-nested-2311" path="assessment/{:id}/maturity-questions-nested/2311" displaytext="8. Cybersecurity Plan" />
                <node id="maturity-questions-nested-2312" path="assessment/{:id}/maturity-questions-nested/2312" displaytext="9. Cybersecurity Exercises" />
                <node id="maturity-questions-nested-2313" displaytext="Information Sharing">
                    <node id="maturity-questions-nested-2331" path="assessment/{:id}/maturity-questions-nested/2331" displaytext="10. External Information Sharing" />
                    <node id="maturity-questions-nested-2332" path="assessment/{:id}/maturity-questions-nested/2332" displaytext="11. Internal Information Sharing" />
                </node>
            </node>
            <node id="maturity-questions-nested-2302" displaytext="Cybersecurity Forces">
                <node id="maturity-questions-nested-2314" path="assessment/{:id}/maturity-questions-nested/2314" displaytext="12. Personnel" />
                <node id="maturity-questions-nested-2315" path="assessment/{:id}/maturity-questions-nested/2315" displaytext="13. Cybersecurity Training" />
            </node>
            <node id="maturity-questions-nested-2303" displaytext="Cybersecurity Controls">
                <node id="maturity-questions-nested-2316" path="assessment/{:id}/maturity-questions-nested/2316" displaytext="14. Authentication and Authorization Controls" />
                <node id="maturity-questions-nested-2317" displaytext="Access Controls">
                    <node id="maturity-questions-nested-2333" path="assessment/{:id}/maturity-questions-nested/2333" displaytext="15. Access Paths" />
                    <node id="maturity-questions-nested-2334" path="assessment/{:id}/maturity-questions-nested/2334" displaytext="16. Remote Access Controls" />
                </node>
                <node id="maturity-questions-nested-2318" displaytext="Cybersecurity Measures">
                    <node id="maturity-questions-nested-2335" path="assessment/{:id}/maturity-questions-nested/2335" displaytext="17. Malicious Code Controls" />
                    <node id="maturity-questions-nested-2336" path="assessment/{:id}/maturity-questions-nested/2336" displaytext="18. Monitoring and Scanning" />
                    <node id="maturity-questions-nested-2337" path="assessment/{:id}/maturity-questions-nested/2337" displaytext="19. Security and Event Log" />
                </node>
                <node id="maturity-questions-nested-2319" path="assessment/{:id}/maturity-questions-nested/2319" displaytext="20. Information Protection" />
                <node id="maturity-questions-nested-2320" path="assessment/{:id}/maturity-questions-nested/2320" displaytext="21. User Training" />
                <node id="maturity-questions-nested-2321" path="assessment/{:id}/maturity-questions-nested/2321" displaytext="22. Defense Sophistication and Compensating Controls" />
            </node>
            <node id="maturity-questions-nested-2304" displaytext="Incident Response">
                <node id="maturity-questions-nested-2322" path="assessment/{:id}/maturity-questions-nested/2322" displaytext="23. Incident Response Measures" />
                <node id="maturity-questions-nested-2323" path="assessment/{:id}/maturity-questions-nested/2323" displaytext="24. Alternate Site and Disaster Recovery" />
            </node>
            <node id="maturity-questions-nested-2305" displaytext="Dependencies">
                <node id="maturity-questions-nested-2324" path="assessment/{:id}/maturity-questions-nested/2324" displaytext="25. Dependencies - Data at Rest" />
                <node id="maturity-questions-nested-2325" path="assessment/{:id}/maturity-questions-nested/2325" displaytext="26. Dependencies - Data in Motion" />
                <node id="maturity-questions-nested-2326" path="assessment/{:id}/maturity-questions-nested/2326" displaytext="27. Dependencies - Data in Process" />
                <node id="maturity-questions-nested-2327" path="assessment/{:id}/maturity-questions-nested/2327" displaytext="28. Dependencies - End Point Systems" />
            </node>
        </node>


        <node displaytext="Statements" id="maturity-questions-acet" path="assessment/{:id}/maturity-questions-acet" visible="INSTALL-MODE:ACET MATURITY:ACET" />
    </node>


    <!-- Results Phase -->
    <node displaytext="Results" id="phase-results">

        <!-- Results - CMMC -->
        <node displaytext="Target and Achieved Levels" id="cmmc-level-results" path="assessment/{:id}/results/cmmc-level-results" visible="MATURITY:CMMC" />
        <node displaytext="Level Drill Down" id="cmmc-level-drilldown" path="assessment/{:id}/results/cmmc-level-drilldown" visible="MATURITY:CMMC" />
        <node displaytext="Compliance Score" id="cmmc-compliance" path="assessment/{:id}/results/cmmc-compliance" visible="MATURITY:CMMC" />
        <node displaytext="Detailed Gaps List" id="cmmc-gaps" path="assessment/{:id}/results/cmmc-gaps" visible="MATURITY:CMMC" />


        <!-- Results - CMMC2 -->
        <node displaytext="Performance by Level" id="cmmc2-level-results" path="assessment/{:id}/results/cmmc2-level-results" visible="MATURITY:CMMC2" />
        <node displaytext="Performance by Domain" id="cmmc2-domain-results" path="assessment/{:id}/results/cmmc2-domain-results" visible="MATURITY:CMMC2" />
        <node displaytext="SPRS Score" id="sprs-score" path="assessment/{:id}/results/sprs-score" visible="MATURITY:CMMC2 TARGET-LEVEL-GT:1" />



        <!-- Results - EDM -->
        <node displaytext="Summary Results" id="summary-results" path="assessment/{:id}/results/summary-results" visible="MATURITY:EDM" />
        <node displaytext="Relationship Formation" id="relationship-formation" path="assessment/{:id}/results/relationship-formation" visible="MATURITY:EDM" />
        <node displaytext="Relationship Management and Governance" id="relationship-management" path="assessment/{:id}/results/relationship-management" visible="MATURITY:EDM" />
        <node displaytext="Service Protection and Sustainment" id="service-protection" path="assessment/{:id}/results/service-protection" visible="MATURITY:EDM" />
        <node displaytext="Maturity Indicator Levels" id="maturity-indicator-levels" path="assessment/{:id}/results/maturity-indicator-levels" visible="MATURITY:EDM" />



        <!-- Results - CRR -->
        <node displaytext="Summary Results" id="crr-summary-results" path="assessment/{:id}/results/crr-summary-results" visible="MATURITY:CRR" />
        <node displaytext="Asset Management" id="crr-domain-am" path="assessment/{:id}/results/crr-domain-am" visible="MATURITY:CRR" />
        <node displaytext="Controls Management" id="crr-domain-cm" path="assessment/{:id}/results/crr-domain-cm" visible="MATURITY:CRR" />
        <node displaytext="Configuration and Change Management" id="crr-domain-ccm" path="assessment/{:id}/results/crr-domain-ccm" visible="MATURITY:CRR" />
        <node displaytext="Vulnerability Management" id="crr-domain-vm" path="assessment/{:id}/results/crr-domain-vm" visible="MATURITY:CRR" />
        <node displaytext="Incident Management" id="crr-domain-im" path="assessment/{:id}/results/crr-domain-im" visible="MATURITY:CRR" />
        <node displaytext="Service Continuity Management" id="crr-domain-scm" path="assessment/{:id}/results/crr-domain-scm" visible="MATURITY:CRR" />
        <node displaytext="Risk Management" id="crr-domain-rm" path="assessment/{:id}/results/crr-domain-rm" visible="MATURITY:CRR" />
        <node displaytext="External Dependencies Management" id="crr-domain-edm" path="assessment/{:id}/results/crr-domain-edm" visible="MATURITY:CRR" />
        <node displaytext="Training and Awareness" id="crr-domain-ta" path="assessment/{:id}/results/crr-domain-ta" visible="MATURITY:CRR" />
        <node displaytext="Situational Awareness" id="crr-domain-sa" path="assessment/{:id}/results/crr-domain-sa" visible="MATURITY:CRR" />



        <!-- Results - RRA -->
        <node displaytext="Goal Performance" id="rra-gaps" path="assessment/{:id}/results/rra-gaps" visible="MATURITY:RRA" />
        <node displaytext="Assessment Tiers" id="rra-level-results" path="assessment/{:id}/results/rra-level-results" visible="MATURITY:RRA" />
        <node displaytext="Performance Summary" id="rra-summary-all" path="assessment/{:id}/results/rra-summary-all" visible="MATURITY:RRA" />



        <!-- Results - ACET -->
        <node displaytext="ACET Maturity Results" id="acet-detail" path="assessment/{:id}/results/acet-detail" visible="MATURITY:ACET" />
        <node displaytext="ACET Dashboard" id="acet-dashboard" path="assessment/{:id}/results/acet-dashboard" visible="MATURITY:ACET" />



        <!-- Results - CIS -->
        <node displaytext="CIS Section Scoring" id="section-scoring" path="assessment/{:id}/results/section-scoring" visible="MATURITY:CIS" />
        <node displaytext="CIS Deficiencies" id="ranked-deficiency" path="assessment/{:id}/results/ranked-deficiency" visible="MATURITY:CIS" />




        <node displaytext="High-Level Assessment Description Executive Summary &amp; Comments" id="overview" path="assessment/{:id}/results/overview" visible="SHOW-EXEC-SUMMARY" />

        <node displaytext="Reports" id="reports" path="assessment/{:id}/results/reports" />

        <node displaytext="Feedback" id="feedback" path="assessment/{:id}/results/feedback" visible="" />

        <node displaytext="Analytics" id="analytics" path="assessment/{:id}/results/analytics" />

        <node displaytext="Assessment Complete" id="tsa-assessment-complete" path="assessment/{:id}/results/tsa-assessment-complete" visible="INSTALL-MODE:TSA" />

    </node>

</nav>