[
	{ "s": "F", "p": [21] },
	{ "s": "FACILITY", "p": [4, 49, 41] },
	{ "s": "FACILITY-SPECIFIC", "p": [4] },
	{ "s": "FACTOR", "p": [58, 48, 67] },
	{ "s": "FACTORS", "p": [58, 48, 67, 4] },
	{ "s": "FAMILIARITY", "p": [10] },
	{ "s": "FAVORING", "p": [5] },
	{ "s": "FEATURE", "p": [16, 68] },
	{ "s": "FEATURES", "p": [28, 27, 16, 43] },
	{ "s": "FEDERAL", "p": [67, 5, 4] },
	{ "s": "FEDERALLY", "p": [4] },
	{ "s": "FEW", "p": [21, 9] },
	{ "s": "FFIEC", "p": [67, 45, 4] },
	{ "s": "FIELD", "p": [43, 24, 66, 65, 64, 63, 62, 52, 46, 44, 34, 26, 21] },
	{ "s": "FIELDS", "p": [44, 43, 11] },
	{ "s": "FIGURE", "p": [8, 24, 44, 25, 16, 61, 17, 9, 56, 55, 54, 53, 52, 51, 49, 48, 43, 42, 39, 38, 37, 32, 30, 29, 28, 27, 21, 15, 11, 10, 59, 58, 50, 46, 35, 34, 33, 31, 26, 23, 22, 20, 19, 18, 14, 13] },
	{ "s": "FILE", "p": [13, 27, 21, 14] },
	{ "s": "FILES", "p": [21] },
	{ "s": "FILLING", "p": [58] },
	{ "s": "FILTER", "p": [56, 49, 48, 26, 24] },
	{ "s": "FILTERS", "p": [56, 48] },
	{ "s": "FINAL", "p": [58] },
	{ "s": "FINALLY", "p": [58] },
	{ "s": "FINANCIAL", "p": [67, 4] },
	{ "s": "FINDING", "p": [67] },
	{ "s": "FINISH", "p": [8] },
	{ "s": "FINISHED", "p": [17] },
	{ "s": "FIPS", "p": [67] },
	{ "s": "FIREWALL", "p": [67] },
	{ "s": "FIRST", "p": [68, 44, 42, 34, 11, 57, 45, 24, 10] },
	{ "s": "FIVE", "p": [45, 4] },
	{ "s": "FIXING", "p": [55] },
	{ "s": "FOCUS", "p": [4] },
	{ "s": "FOCUSING", "p": [63, 51] },
	{ "s": "FOLDER", "p": [8, 14] },
	{ "s": "FOLLOW", "p": [8] },
	{ "s": "FOLLOWED", "p": [10] },
	{ "s": "FOLLOWING", "p": [4, 47, 41, 17, 10] },
	{ "s": "FOR", "p": [49, 27, 24, 4, 67, 64, 43, 55, 16, 25, 58, 45, 21, 48, 15, 52, 33, 26, 17, 10, 62, 59, 46, 38, 11, 5, 68, 66, 63, 61, 60, 56, 54, 53, 51, 44, 41, 39, 37, 34, 22, 8, 7, 6] },
	{ "s": "FORGET", "p": [34] },
	{ "s": "FORGOT", "p": [11] },
	{ "s": "FORGOTTEN", "p": [11] },
	{ "s": "FORMAL", "p": [67, 43] },
	{ "s": "FORMALITY", "p": [67] },
	{ "s": "FORMALLY", "p": [67] },
	{ "s": "FORMAT", "p": [67, 43, 21] },
	{ "s": "FORMATTED", "p": [24] },
	{ "s": "FORMING", "p": [10] },
	{ "s": "FORTH", "p": [63] },
	{ "s": "FOUND", "p": [59, 53, 51, 25, 19] },
	{ "s": "FRAMEWORK", "p": [7, 4] },
	{ "s": "FREE", "p": [7] },
	{ "s": "FREQUENCY", "p": [17] },
	{ "s": "FROM", "p": [59, 51, 45, 44, 10, 5, 4, 67, 66, 65, 64, 63, 62, 58, 49, 43, 34, 32, 30, 29, 28, 25, 21, 20, 11, 7] },
	{ "s": "FRONTLINE", "p": [67] },
	{ "s": "FULL", "p": [68, 49, 24, 21] },
	{ "s": "FULL-SCREEN", "p": [21] },
	{ "s": "FULLY", "p": [58, 48, 4] },
	{ "s": "FUNCTION", "p": [60] },
	{ "s": "FUNCTIONAL", "p": [10, 4] },
	{ "s": "FUNCTIONALITY", "p": [9] },
	{ "s": "FUNCTIONS", "p": [67, 59, 15] },
	{ "s": "FURTHER", "p": [67, 49] },
	{ "s": "FUTURE", "p": [49] }
]