[
	{ "s": "LANGUAGE", "p": [14] },
	{ "s": "LARGE", "p": [27, 26, 14, 13] },
	{ "s": "LARGEST", "p": [27] },
	{ "s": "LASTING", "p": [11] },
	{ "s": "LAYOUT", "p": [14] },
	{ "s": "LEAD", "p": [18, 11] },
	{ "s": "LEADERS", "p": [13] },
	{ "s": "LEADERSHIP", "p": [11] },
	{ "s": "LEADING", "p": [13] },
	{ "s": "LEARNED", "p": [11] },
	{ "s": "LEAST", "p": [26] },
	{ "s": "LEAVE", "p": [27] },
	{ "s": "LED", "p": [8] },
	{ "s": "LEFT", "p": [16] },
	{ "s": "LEGACY", "p": [28] },
	{ "s": "LEGAL", "p": [27] },
	{ "s": "LEGISLATION", "p": [21] },
	{ "s": "LENGTH", "p": [14] },
	{ "s": "LESS", "p": [18] },
	{ "s": "LESSONS", "p": [11] },
	{ "s": "LETTER", "p": [14] },
	{ "s": "LEVEL", "p": [16, 27, 18, 17, 11, 26, 22, 21, 20, 9] },
	{ "s": "LEVELS", "p": [16, 19, 11, 27, 25, 18, 17] },
	{ "s": "LEVERAGING", "p": [18] },
	{ "s": "LIBRARY", "p": [28] },
	{ "s": "LIFECYCLE", "p": [11, 9] },
	{ "s": "LIFECYCLE—FROM", "p": [11] },
	{ "s": "LIGHTS", "p": [26] },
	{ "s": "LIGHTWEIGHT", "p": [8] },
	{ "s": "LIKE", "p": [13] },
	{ "s": "LIKELY", "p": [11] },
	{ "s": "LIKEWISE", "p": [13] },
	{ "s": "LIMIT", "p": [27] },
	{ "s": "LIMITED", "p": [27] },
	{ "s": "LINE", "p": [19, 13] },
	{ "s": "LINEAR", "p": [18] },
	{ "s": "LINKED", "p": [27] },
	{ "s": "LIST", "p": [22, 21, 26, 19, 18, 6] },
	{ "s": "LISTED", "p": [19] },
	{ "s": "LISTS", "p": [19] },
	{ "s": "LOCALITY", "p": [27] },
	{ "s": "LOCATE", "p": [19] },
	{ "s": "LOCATED", "p": [14] },
	{ "s": "LOCATION", "p": [27] },
	{ "s": "LOGICAL", "p": [27] },
	{ "s": "LOGISTICAL", "p": [13] },
	{ "s": "LOGISTICS", "p": [13] },
	{ "s": "LOWER", "p": [16, 19, 11] }
]