[
	{ "s": "P", "p": [92, 131] },
	{ "s": "PACK", "p": [8] },
	{ "s": "PACKET", "p": [136] },
	{ "s": "PACKETS", "p": [84] },
	{ "s": "PAGE", "p": [88, 131, 92, 50, 34, 130, 134, 87, 19, 133, 97, 93, 86, 26, 17, 10, 5, 132, 90, 80, 71, 66, 65, 64, 30, 29, 25, 23, 20, 18, 16, 14, 11] },
	{ "s": "PAGES", "p": [87, 33, 136, 131, 130, 129, 93, 92, 84, 66, 49] },
	{ "s": "PAGING", "p": [138] },
	{ "s": "PAINT", "p": [90] },
	{ "s": "PALETTE", "p": [77] },
	{ "s": "PAN", "p": [92] },
	{ "s": "PANE", "p": [12, 81] },
	{ "s": "PANEL", "p": [88, 101, 75, 93, 80, 96, 82, 81, 79, 77, 52, 118, 115, 113, 112, 102, 92, 78, 21] },
	{ "s": "PANELS", "p": [93, 89, 75] },
	{ "s": "PAPER", "p": [86, 88, 66] },
	{ "s": "PAPERS", "p": [137, 31] },
	{ "s": "PARAGRAPH", "p": [92] },
	{ "s": "PARAMETER", "p": [22, 20, 139] },
	{ "s": "PARAMETERS", "p": [22, 131, 130, 20] },
	{ "s": "PARAMOUNT", "p": [66] },
	{ "s": "PART", "p": [66, 90, 88, 84, 81, 75, 72, 69, 48, 5] },
	{ "s": "PART-I", "p": [66] },
	{ "s": "PART-II", "p": [66] },
	{ "s": "PARTIAL", "p": [69, 72] },
	{ "s": "PARTICIPATE", "p": [69] },
	{ "s": "PARTICIPATION", "p": [69] },
	{ "s": "PARTICULAR", "p": [82, 77, 83, 69, 136, 124, 113, 112] },
	{ "s": "PARTICULARLY", "p": [69, 63] },
	{ "s": "PARTIES", "p": [136] },
	{ "s": "PARTNER", "p": [84] },
	{ "s": "PARTNERS", "p": [69] },
	{ "s": "PARTS", "p": [66, 109, 87, 75, 69, 51, 25] },
	{ "s": "PARTY", "p": [136] },
	{ "s": "PASSED", "p": [123, 122, 121, 84] },
	{ "s": "PASSWORD", "p": [36, 14, 136, 34, 12, 117, 66, 35] },
	{ "s": "PASSWORD-CRACKING", "p": [136] },
	{ "s": "PASSWORDS", "p": [136, 36] },
	{ "s": "PAST", "p": [66] },
	{ "s": "PASTE", "p": [87, 92, 79, 138, 77, 25] },
	{ "s": "PASTED", "p": [75] },
	{ "s": "PASTES", "p": [87] },
	{ "s": "PASTING", "p": [87] },
	{ "s": "PATH", "p": [78, 90] },
	{ "s": "PATHS", "p": [90, 63] },
	{ "s": "PATTERN", "p": [90] },
	{ "s": "PAYMENT", "p": [66, 137] },
	{ "s": "PAYROLL", "p": [136] },
	{ "s": "PC", "p": [84] },
	{ "s": "PCI", "p": [66] },
	{ "s": "PCIDSS", "p": [137] },
	{ "s": "PDF", "p": [37, 137, 8] },
	{ "s": "PEAK", "p": [56] },
	{ "s": "PENALTIES", "p": [56] },
	{ "s": "PENCIL", "p": [88] },
	{ "s": "PENETRATION", "p": [66] },
	{ "s": "PENTAGON", "p": [80] },
	{ "s": "PENTIUM", "p": [8] },
	{ "s": "PEOPLE", "p": [56, 63, 59, 58, 57, 77, 82] },
	{ "s": "PER", "p": [133, 124, 63] },
	{ "s": "PERCENT", "p": [63, 133, 124, 60, 131, 120, 93] },
	{ "s": "PERCENTAGE", "p": [133, 124, 122, 121, 119, 131, 130, 120, 88] },
	{ "s": "PERCENTAGES", "p": [116] },
	{ "s": "PERFORM", "p": [137, 69, 136, 87, 66, 63, 32, 22, 13, 4] },
	{ "s": "PERFORMANCE", "p": [66, 138, 137, 68] },
	{ "s": "PERFORMED", "p": [122, 121, 87, 67, 66, 13] },
	{ "s": "PERFORMING", "p": [136, 66, 13, 5] },
	{ "s": "PERHAPS", "p": [80] },
	{ "s": "PERIMETER", "p": [90, 80] },
	{ "s": "PERIMETERS", "p": [66] },
	{ "s": "PERIOD", "p": [82, 137, 83, 77, 63] },
	{ "s": "PERIPHERALS", "p": [84] },
	{ "s": "PERMANENTLY", "p": [88, 63] },
	{ "s": "PERMISSION", "p": [6] },
	{ "s": "PERMISSIONS", "p": [12] },
	{ "s": "PERMITS", "p": [63] },
	{ "s": "PERMITTING", "p": [62] },
	{ "s": "PERSIST", "p": [12] },
	{ "s": "PERSON", "p": [134, 130, 129, 84, 81, 63] },
	{ "s": "PERSONAL", "p": [137, 84, 66, 63] },
	{ "s": "PERSONALLY", "p": [137, 66] },
	{ "s": "PERSONNEL", "p": [66, 136, 69, 63] },
	{ "s": "PERSONS", "p": [63] },
	{ "s": "PERSPECTIVE", "p": [96] },
	{ "s": "PERTAIN", "p": [112] },
	{ "s": "PERTAINING", "p": [139, 77] },
	{ "s": "PERTAINS", "p": [112] },
	{ "s": "PERTINENT", "p": [66] },
	{ "s": "PERVASIVE", "p": [66] },
	{ "s": "PHARMACEUTICAL", "p": [66] },
	{ "s": "PHI", "p": [66] },
	{ "s": "PHONE", "p": [84, 78] },
	{ "s": "PHRASE", "p": [32] },
	{ "s": "PHYSICAL", "p": [66, 82, 81, 77, 136, 117, 106, 88, 84, 78, 63, 61, 8, 5, 4] },
	{ "s": "PHYSICALLY", "p": [77] },
	{ "s": "PICK", "p": [86, 25, 15] },
	{ "s": "PICKER", "p": [51] },
	{ "s": "PICTURE", "p": [78, 130, 124, 86, 73] },
	{ "s": "PIE", "p": [130] },
	{ "s": "PIECE", "p": [83, 82, 77] },
	{ "s": "PII", "p": [66, 137] },
	{ "s": "PILL", "p": [64] },
	{ "s": "PINCH", "p": [92] },
	{ "s": "PIPE", "p": [87] },
	{ "s": "PIPELINE", "p": [66, 139] },
	{ "s": "PIPELINES", "p": [66] },
	{ "s": "PLACE", "p": [69, 87, 80, 66, 63, 133, 129, 115, 96, 93, 88, 83, 82, 81, 77, 73, 25] },
	{ "s": "PLACED", "p": [138, 81, 80, 77, 136, 112, 75] },
	{ "s": "PLACEHOLDERS", "p": [90] },
	{ "s": "PLACES", "p": [88, 66] },
	{ "s": "PLACING", "p": [85, 77] },
	{ "s": "PLAN", "p": [133, 129, 13, 139, 131, 96, 76, 66, 63, 56, 5] },
	{ "s": "PLAN/EMERGENCY", "p": [13] },
	{ "s": "PLANNED", "p": [133, 129] },
	{ "s": "PLANNING", "p": [83, 82, 78, 77, 66] },
	{ "s": "PLANS", "p": [66, 13, 69, 63, 31] },
	{ "s": "PLANT", "p": [63, 81] },
	{ "s": "PLANTS", "p": [66] },
	{ "s": "PLANT’S", "p": [63] },
	{ "s": "PLATFORMS", "p": [66, 8] },
	{ "s": "PLAY", "p": [138] },
	{ "s": "PLC", "p": [137, 84] },
	{ "s": "PLCS", "p": [66] },
	{ "s": "PLEASE", "p": [132, 12] },
	{ "s": "PLUS", "p": [88, 131, 129, 82, 75, 66] },
	{ "s": "PNG", "p": [86, 77] },
	{ "s": "POINT", "p": [78, 90, 80, 93, 89, 138, 137, 133, 130, 92, 88, 86, 66, 28, 16] },
	{ "s": "POINTER", "p": [79] },
	{ "s": "POINTS", "p": [80, 78, 90, 88, 136, 66, 41, 5] },
	{ "s": "POLICIES", "p": [82, 69, 13, 4, 83, 77, 66, 6] },
	{ "s": "POLICY", "p": [66, 69, 33, 137, 84, 13, 5] },
	{ "s": "POLISH", "p": [77] },
	{ "s": "POLYLINE", "p": [78] },
	{ "s": "POOR", "p": [66] },
	{ "s": "POORLY", "p": [136] },
	{ "s": "POPULAR", "p": [93] },
	{ "s": "POPULARITY", "p": [33] },
	{ "s": "POPULATE", "p": [131, 52] },
	{ "s": "POPULATED", "p": [53] },
	{ "s": "POPULATION", "p": [63] },
	{ "s": "POPUP", "p": [112, 83, 82, 78, 77, 138, 113, 94, 88] },
	{ "s": "PORT", "p": [90, 12, 11, 8] },
	{ "s": "PORTABILITY", "p": [66, 139, 137] },
	{ "s": "PORTABLE", "p": [137, 63] },
	{ "s": "PORTALS", "p": [136] },
	{ "s": "PORTION", "p": [96, 72] },
	{ "s": "PORTS", "p": [12] },
	{ "s": "POSE", "p": [66] },
	{ "s": "POSITION", "p": [93, 80, 90, 77, 138, 131, 89, 78] },
	{ "s": "POSITIONED", "p": [90] },
	{ "s": "POSITIVE", "p": [96, 133, 131, 124, 122, 121, 120] },
	{ "s": "POSITIVELY", "p": [131, 129] },
	{ "s": "POSSESS", "p": [69] },
	{ "s": "POSSIBLE", "p": [138, 80, 79, 124, 117, 87, 78, 63, 32] },
	{ "s": "POSSIBLY", "p": [63] },
	{ "s": "POSTURE", "p": [4, 136, 115, 114, 96, 5] },
	{ "s": "POSTURES", "p": [13] },
	{ "s": "POTENTIAL", "p": [56, 109, 63, 4, 136, 129, 69, 66, 64, 55] },
	{ "s": "POTENTIALLY", "p": [136, 109, 72, 66, 63] },
	{ "s": "POUND", "p": [28] },
	{ "s": "POWER", "p": [66, 63, 84, 72, 61] },
	{ "s": "POWERFUL", "p": [105] },
	{ "s": "PRACTICE", "p": [66, 32] },
	{ "s": "PRACTICES", "p": [69, 66, 4, 5, 32] },
	{ "s": "PRE", "p": [86, 80, 73, 28] },
	{ "s": "PRE-BUILT", "p": [73] },
	{ "s": "PRE-DEFINED", "p": [28] },
	{ "s": "PRE-EXISTING", "p": [80] },
	{ "s": "PRE-INSTALLED", "p": [86] },
	{ "s": "PRECAUTIONS", "p": [66] },
	{ "s": "PRECEDENCE", "p": [113, 112, 87] },
	{ "s": "PREDEFINED", "p": [81] },
	{ "s": "PREDICATED", "p": [66] },
	{ "s": "PREDICTIVE", "p": [69] },
	{ "s": "PREFERRED", "p": [89, 8] },
	{ "s": "PREFIXED", "p": [90] },
	{ "s": "PRELIMINARY", "p": [13] },
	{ "s": "PRELOADED", "p": [77] },
	{ "s": "PREPARATION", "p": [44, 13, 50, 49, 5, 139, 102, 65, 51, 48, 46, 43] },
	{ "s": "PREPARE", "p": [49, 75, 74, 44] },
	{ "s": "PREPARED", "p": [13, 6, 98, 72] },
	{ "s": "PREPARING", "p": [7] },
	{ "s": "PREREQUISITES", "p": [12] },
	{ "s": "PRESCRIBED", "p": [66] },
	{ "s": "PRESCRIBES", "p": [66] },
	{ "s": "PRESCRIPTIVE", "p": [63] },
	{ "s": "PRESENT", "p": [124, 59, 58, 57, 56, 5] },
	{ "s": "PRESENTATION", "p": [125, 124, 5] },
	{ "s": "PRESENTED", "p": [72, 5, 112, 133, 131, 129, 124, 96, 82, 77, 69, 63, 28] },
	{ "s": "PRESENTS", "p": [66, 131, 69, 133, 84, 32] },
	{ "s": "PRESERVE", "p": [80] },
	{ "s": "PRESERVED", "p": [28] },
	{ "s": "PRESERVING", "p": [137] },
	{ "s": "PRESIDENT", "p": [66] },
	{ "s": "PRESS", "p": [32] },
	{ "s": "PRESSES", "p": [32] },
	{ "s": "PRESSING", "p": [87] },
	{ "s": "PRESUMED", "p": [66] },
	{ "s": "PREVENT", "p": [63, 84, 66] },
	{ "s": "PREVENTED", "p": [12] },
	{ "s": "PREVENTION", "p": [84] },
	{ "s": "PREVIEW", "p": [86] },
	{ "s": "PREVIOUS", "p": [138, 92, 73, 69, 13, 12, 130, 87, 64, 22] },
	{ "s": "PREVIOUSLY", "p": [12, 89, 65, 52, 25, 13] },
	{ "s": "PRIMARILY", "p": [137, 72] },
	{ "s": "PRIMARY", "p": [137, 4, 96, 66, 56, 28, 13, 5] },
	{ "s": "PRIMITIVE", "p": [90] },
	{ "s": "PRIMITIVES", "p": [90] },
	{ "s": "PRINCIPAL", "p": [134, 131, 130, 33] },
	{ "s": "PRINCIPLE", "p": [69] },
	{ "s": "PRINT", "p": [127, 86, 114, 92] },
	{ "s": "PRINTABLE", "p": [5] },
	{ "s": "PRINTED", "p": [129, 94, 5] },
	{ "s": "PRINTER", "p": [84, 137] },
	{ "s": "PRINTING", "p": [5] },
	{ "s": "PRIOR", "p": [5, 8, 13, 6] },
	{ "s": "PRIORITIES", "p": [117, 69] },
	{ "s": "PRIORITIZATION", "p": [69] },
	{ "s": "PRIORITIZE", "p": [66] },
	{ "s": "PRIORITIZED", "p": [120, 32] },
	{ "s": "PRIORITIZING", "p": [131, 66] },
	{ "s": "PRIORITY", "p": [117, 116, 66] },
	{ "s": "PRIVACY", "p": [66, 137] },
	{ "s": "PRIVATE", "p": [137, 66, 136, 84, 6] },
	{ "s": "PRIVILEGE", "p": [136] },
	{ "s": "PRIVILEGES", "p": [66, 12] },
	{ "s": "PRO", "p": [12] },
	{ "s": "PROACTIVE", "p": [66] },
	{ "s": "PROBABLY", "p": [66] },
	{ "s": "PROBES", "p": [136] },
	{ "s": "PROBLEM", "p": [138, 109, 82, 77, 63] },
	{ "s": "PROBLEMS", "p": [134, 117, 109, 41, 63] },
	{ "s": "PROCEDURAL", "p": [66, 4] },
	{ "s": "PROCEDURE", "p": [12, 9, 13] },
	{ "s": "PROCEDURES", "p": [66, 69, 13, 137, 109, 63, 33] },
	{ "s": "PROCEED", "p": [136] },
	{ "s": "PROCESS", "p": [69, 66, 5, 4, 106, 105, 96, 84, 63, 50, 12, 139, 134, 114, 110, 102, 95, 77, 65, 64, 54, 52, 49, 46, 44, 20, 16, 13, 10] },
	{ "s": "PROCESSES", "p": [69, 66, 139, 134, 131, 13, 6, 4] },
	{ "s": "PROCESSING", "p": [66, 137, 136, 93, 64, 25, 5] },
	{ "s": "PROCESSING—INCLUDING", "p": [66] },
	{ "s": "PROCESSOR", "p": [84, 8, 138] },
	{ "s": "PROCESSORS", "p": [66] },
	{ "s": "PROCUREMENT", "p": [33] },
	{ "s": "PRODUCE", "p": [93, 87, 80] },
	{ "s": "PRODUCES", "p": [129, 131] },
	{ "s": "PRODUCING", "p": [63] },
	{ "s": "PRODUCT", "p": [63, 6, 66, 61, 12, 1] },
	{ "s": "PRODUCTION", "p": [63, 61, 136, 66] },
	{ "s": "PRODUCTIVITY", "p": [136] },
	{ "s": "PRODUCTS", "p": [66, 136, 69, 60, 6] },
	{ "s": "PROFESSIONALS", "p": [4] },
	{ "s": "PROFILE", "p": [34, 35, 69, 19, 11, 95, 12] },
	{ "s": "PROFILES", "p": [69, 66] },
	{ "s": "PROGRAM", "p": [69, 136, 66, 63, 10, 6, 4, 5] },
	{ "s": "PROGRAMMABLE", "p": [137, 84, 66] },
	{ "s": "PROGRAMMATIC", "p": [66, 4] },
	{ "s": "PROGRAMS", "p": [136, 66, 137, 93, 33] },
	{ "s": "PROGRESS", "p": [101, 96] },
	{ "s": "PROGRESSING", "p": [69] },
	{ "s": "PROMPT", "p": [136] },
	{ "s": "PROP", "p": [82, 81, 80, 79, 78] },
	{ "s": "PROPAGATE", "p": [82, 83, 77] },
	{ "s": "PROPAGATED", "p": [124] },
	{ "s": "PROPER", "p": [23, 12, 6] },
	{ "s": "PROPERLY", "p": [12] },
	{ "s": "PROPERTIES", "p": [77, 81, 138, 112, 78, 12, 113, 88, 87, 80] },
	{ "s": "PROPERTY", "p": [77, 60, 139, 138, 63, 6] },
	{ "s": "PROPORTIONS", "p": [123, 92] },
	{ "s": "PROPRIETARY", "p": [137] },
	{ "s": "PROTECT", "p": [66, 69, 5] },
	{ "s": "PROTECTED", "p": [23, 20, 136, 66, 65] },
	{ "s": "PROTECTING", "p": [66, 137, 131] },
	{ "s": "PROTECTION", "p": [66, 137, 82, 77, 136, 131, 73, 69, 32, 4] },
	{ "s": "PROTECTIONS", "p": [66] },
	{ "s": "PROTECTS", "p": [66] },
	{ "s": "PROTOCOL", "p": [84, 77] },
	{ "s": "PROVIDE", "p": [66, 96, 5, 138, 109, 69, 6, 136, 130, 129, 127, 114, 90, 86, 81, 63, 62, 61, 60, 59, 58, 57, 53, 51, 21, 12] },
	{ "s": "PROVIDED", "p": [136, 5, 133, 51, 13, 138, 130, 128, 117, 82, 73, 69, 66, 63, 56, 26, 12, 6, 4] },
	{ "s": "PROVIDERS", "p": [66] },
	{ "s": "PROVIDES", "p": [66, 4, 131, 129, 116, 82, 80, 65, 5, 133, 130, 81, 73, 21, 137, 134, 127, 126, 124, 115, 114, 109, 88, 86, 84, 83, 79, 78, 77, 72, 69, 64, 63, 54, 53, 51, 41, 35, 32, 20] },
	{ "s": "PROVIDING", "p": [84, 82, 77, 66] },
	{ "s": "PROVINCE", "p": [51] },
	{ "s": "PROVISIONAL", "p": [64] },
	{ "s": "PROVISIONS", "p": [66] },
	{ "s": "PROXIMITY", "p": [94, 63] },
	{ "s": "PROXY", "p": [66, 63] },
	{ "s": "PSTN", "p": [84] },
	{ "s": "PUB", "p": [66] },
	{ "s": "PUB.L", "p": [66] },
	{ "s": "PUBLIC", "p": [137, 136, 84, 78, 66, 131, 23, 20] },
	{ "s": "PUBLICATION", "p": [66, 64, 139, 137, 33, 32, 5] },
	{ "s": "PUBLISH", "p": [127] },
	{ "s": "PUBLISHER", "p": [33] },
	{ "s": "PUBLISHING", "p": [5] },
	{ "s": "PULL", "p": [90] },
	{ "s": "PULLED", "p": [66, 29] },
	{ "s": "PULLS", "p": [4] },
	{ "s": "PULP", "p": [66] },
	{ "s": "PUMP", "p": [77] },
	{ "s": "PUMPING", "p": [88, 82, 77] },
	{ "s": "PURCHASED", "p": [66] },
	{ "s": "PURPLE", "p": [82] },
	{ "s": "PURPOSE", "p": [66, 21] },
	{ "s": "PURPOSEFUL", "p": [66] },
	{ "s": "PURPOSES", "p": [82, 78, 77, 83, 66, 12, 6, 3] },
	{ "s": "PURSUANT", "p": [137] },
	{ "s": "PUT", "p": [138, 66] },
	{ "s": "PX", "p": [92] }
]