[
	{ "s": "M", "p": [137, 86, 129, 81] },
	{ "s": "MAC", "p": [136, 86, 129, 75] },
	{ "s": "MACHINE", "p": [78, 136] },
	{ "s": "MACHINERY", "p": [64, 61] },
	{ "s": "MACHINES", "p": [78, 64] },
	{ "s": "MADE", "p": [138, 125, 116, 53, 25, 5] },
	{ "s": "MAGNETIC", "p": [78] },
	{ "s": "MAGNIFYING", "p": [87, 33] },
	{ "s": "MAIL", "p": [78] },
	{ "s": "MAILING", "p": [6] },
	{ "s": "MAILS", "p": [78] },
	{ "s": "MAIN", "p": [82, 48, 96, 91, 137, 118, 116, 113, 99, 78, 72, 70, 51, 47, 44, 34, 24, 5] },
	{ "s": "MAINS", "p": [78] },
	{ "s": "MAINTAIN", "p": [86, 75, 55, 24, 22, 16] },
	{ "s": "MAINTENANCE", "p": [64, 9, 5, 136, 72, 34] },
	{ "s": "MAJOR", "p": [136, 94, 89, 67] },
	{ "s": "MAJORITY", "p": [119] },
	{ "s": "MAKE", "p": [137, 83, 82, 81, 78, 73, 138, 135, 127, 27] },
	{ "s": "MAKER", "p": [9] },
	{ "s": "MAKES", "p": [129, 87, 84, 78, 67, 53, 27] },
	{ "s": "MAKEUP", "p": [129] },
	{ "s": "MAKING", "p": [137, 82, 74] },
	{ "s": "MALFUNCTION", "p": [64] },
	{ "s": "MALICIOUS", "p": [135, 78, 89] },
	{ "s": "MALWARE", "p": [135, 119, 89] },
	{ "s": "MAN", "p": [135] },
	{ "s": "MAN-IN-THE-MIDDLE", "p": [135] },
	{ "s": "MANAGE", "p": [27, 78, 25, 24, 23] },
	{ "s": "MANAGED", "p": [108, 78] },
	{ "s": "MANAGEMENT", "p": [9, 119, 78, 53, 64, 55, 138, 136, 125, 89, 52, 31, 5] },
	{ "s": "MANAGER", "p": [137, 129, 127] },
	{ "s": "MANAGING", "p": [78, 91] },
	{ "s": "MANIPULATE", "p": [135, 73] },
	{ "s": "MANIPULATED", "p": [73] },
	{ "s": "MANIPULATION", "p": [135] },
	{ "s": "MANIPULATIONS", "p": [73] },
	{ "s": "MANNER", "p": [135, 67] },
	{ "s": "MANOMETERS", "p": [78] },
	{ "s": "MANUAL", "p": [85, 78, 73, 64, 48] },
	{ "s": "MANUALLY", "p": [77, 51] },
	{ "s": "MANUALS", "p": [64, 9] },
	{ "s": "MANUFACTURING", "p": [89] },
	{ "s": "MANY", "p": [78, 111, 67, 131, 107, 98, 97, 86, 83, 77, 65, 64, 55, 18, 5, 4] },
	{ "s": "MAPPED", "p": [131] },
	{ "s": "MAPPING", "p": [65] },
	{ "s": "MAPS", "p": [64, 108] },
	{ "s": "MARCH", "p": [138] },
	{ "s": "MARK", "p": [97, 108] },
	{ "s": "MARKED", "p": [129, 72, 112, 91, 130, 116, 113, 109, 107, 97, 73, 5] },
	{ "s": "MARKING", "p": [108, 101, 82, 72] },
	{ "s": "MARKS", "p": [65, 33] },
	{ "s": "MARLIN", "p": [138] },
	{ "s": "MASTER", "p": [78] },
	{ "s": "MATCH", "p": [131, 122, 121, 116, 109, 108, 84, 82, 72] },
	{ "s": "MATCHES", "p": [123] },
	{ "s": "MATCHING", "p": [81, 113, 25] },
	{ "s": "MATERIAL", "p": [64, 136, 24] },
	{ "s": "MATERIALS", "p": [64, 57, 5, 63, 60, 59, 58, 24] },
	{ "s": "MATTER", "p": [9, 129, 127, 113, 67, 5, 4] },
	{ "s": "MATURITY", "p": [138, 92, 107, 136, 14] },
	{ "s": "MAXIMIZE", "p": [70] },
	{ "s": "MAXIMIZED", "p": [118, 70] },
	{ "s": "MAXIMIZING", "p": [82] },
	{ "s": "MAXIMUM", "p": [134, 64, 60, 59, 58, 57] },
	{ "s": "MAY", "p": [135, 64, 137, 72, 78, 89, 108, 73, 67, 5, 138, 123, 91, 76, 74, 65, 100, 81, 57, 136, 131, 129, 128, 127, 118, 109, 105, 84, 82, 77, 71, 68, 60, 59, 58, 45, 42, 34, 33, 31, 30, 29, 26, 25, 24, 22, 9, 6, 4] },
	{ "s": "MAYBE", "p": [113] },
	{ "s": "MEANING", "p": [131] },
	{ "s": "MEANS", "p": [135, 136, 108, 84, 73, 4, 129, 112, 111, 97, 89, 82, 72, 67, 29] },
	{ "s": "MEASURE", "p": [78, 110, 55] },
	{ "s": "MEASUREMENT", "p": [78] },
	{ "s": "MEASURES", "p": [34, 136, 78] },
	{ "s": "MEASURING", "p": [78, 63, 62, 61, 60, 59, 58] },
	{ "s": "MECHANICAL", "p": [78] },
	{ "s": "MEDIA", "p": [78] },
	{ "s": "MEDIAN", "p": [134] },
	{ "s": "MEDICAL", "p": [78, 138, 72, 62] },
	{ "s": "MEDICATIONS", "p": [78] },
	{ "s": "MEDICINAL", "p": [78] },
	{ "s": "MEDICINE", "p": [78] },
	{ "s": "MEDIUM", "p": [105, 98, 65] },
	{ "s": "MEET", "p": [127, 66] },
	{ "s": "MEETING", "p": [131] },
	{ "s": "MEETINGS", "p": [125, 78] },
	{ "s": "MEETS", "p": [91] },
	{ "s": "MELLITUS", "p": [78] },
	{ "s": "MEMBERS", "p": [78, 9] },
	{ "s": "MEMORY", "p": [135] },
	{ "s": "MENTIONED", "p": [123, 111] },
	{ "s": "MENU", "p": [16, 38, 47, 46, 45, 15, 83, 82, 84, 81, 79, 73, 85, 80, 137, 70, 35, 87, 44, 24, 17, 86, 36, 138, 75, 72, 51, 43, 41, 40, 39, 29, 5] },
	{ "s": "MENUS", "p": [44, 83, 70] },
	{ "s": "MERCHANDISE", "p": [78] },
	{ "s": "MERELY", "p": [131] },
	{ "s": "MESSAGE", "p": [107, 88, 21, 135, 134, 133, 124, 65, 53] },
	{ "s": "MESSAGES", "p": [124, 135, 78, 21] },
	{ "s": "MET", "p": [91, 131, 66, 5] },
	{ "s": "META", "p": [86] },
	{ "s": "METADATA", "p": [81, 72, 86] },
	{ "s": "METAL", "p": [78] },
	{ "s": "METER", "p": [78] },
	{ "s": "METERS", "p": [78] },
	{ "s": "METHOD", "p": [78, 91, 64, 137, 136, 129, 110, 101, 84, 81, 65] },
	{ "s": "METHODOLOGY", "p": [4] },
	{ "s": "METHODS", "p": [136, 110, 34, 4] },
	{ "s": "MICROCOMPUTER", "p": [78] },
	{ "s": "MICROPROCESSOR", "p": [78] },
	{ "s": "MICROPROCESSOR-BASED", "p": [78] },
	{ "s": "MICROSOFT", "p": [78, 138, 137, 74] },
	{ "s": "MICROWAVE", "p": [78, 73] },
	{ "s": "MIDDLE", "p": [135, 84, 83, 77, 73] },
	{ "s": "MIGHT", "p": [135, 64, 136, 73, 137, 113, 75, 72, 18] },
	{ "s": "MIL", "p": [136] },
	{ "s": "MILES", "p": [76] },
	{ "s": "MILITARY", "p": [89] },
	{ "s": "MILLISECONDS", "p": [81] },
	{ "s": "MIND", "p": [122, 121] },
	{ "s": "MINIATURE", "p": [82] },
	{ "s": "MINIMAL", "p": [29] },
	{ "s": "MINIMIZE", "p": [137, 72] },
	{ "s": "MINIMIZING", "p": [82] },
	{ "s": "MINIMUM", "p": [134, 64] },
	{ "s": "MINOR", "p": [136, 64] },
	{ "s": "MINUS", "p": [77] },
	{ "s": "MISMATCHES", "p": [78] },
	{ "s": "MISSED", "p": [31, 129, 128, 127, 113, 91, 5] },
	{ "s": "MISSES", "p": [64, 9] },
	{ "s": "MISSION", "p": [136, 129] },
	{ "s": "MISSPELLED", "p": [33] },
	{ "s": "MISUSE", "p": [136] },
	{ "s": "MITERLIMIT", "p": [84] },
	{ "s": "MITIGATE", "p": [64, 5] },
	{ "s": "MITIGATION", "p": [64] },
	{ "s": "MITIGATIONS", "p": [4] },
	{ "s": "MIX", "p": [70] },
	{ "s": "MIXED", "p": [135] },
	{ "s": "MIXED-USE", "p": [135] },
	{ "s": "MIXTURES", "p": [64] },
	{ "s": "MOBILE", "p": [78, 138] },
	{ "s": "MODALITIES", "p": [78] },
	{ "s": "MODE", "p": [94, 93, 67, 95, 66, 99, 98, 112, 25, 137, 91, 129, 96, 74, 5, 131, 113, 138, 97, 81, 78, 46, 38, 31, 30, 29, 26, 20, 16] },
	{ "s": "MODEL", "p": [138, 14, 136, 107, 92] },
	{ "s": "MODELED", "p": [5] },
	{ "s": "MODELS", "p": [138, 107, 72] },
	{ "s": "MODEM", "p": [78, 89, 136] },
	{ "s": "MODEMS", "p": [89] },
	{ "s": "MODERATE", "p": [136, 65, 57, 56, 113, 131, 129, 76, 72] },
	{ "s": "MODERN", "p": [138] },
	{ "s": "MODES", "p": [93, 67, 137, 99, 91, 65] },
	{ "s": "MODIFICATION", "p": [136] },
	{ "s": "MODIFICATIONS", "p": [138] },
	{ "s": "MODIFIED", "p": [138, 72, 87, 82, 73] },
	{ "s": "MODIFY", "p": [70, 87, 73, 72, 24] },
	{ "s": "MODULATES", "p": [78] },
	{ "s": "MODULATES/DEMODULATES", "p": [78] },
	{ "s": "MODULE", "p": [24, 22, 21, 23, 16, 19, 138, 25, 26] },
	{ "s": "MODULE(S", "p": [24] },
	{ "s": "MODULES", "p": [24, 22, 16, 138, 27, 23, 21, 19] },
	{ "s": "MODULE’S", "p": [24, 22] },
	{ "s": "MONEY", "p": [57] },
	{ "s": "MONEY-BASED", "p": [57] },
	{ "s": "MONITOR", "p": [78, 89, 135] },
	{ "s": "MONITORED", "p": [135, 78] },
	{ "s": "MONITORING", "p": [78, 119] },
	{ "s": "MONITORS", "p": [78] },
	{ "s": "MORE", "p": [5, 16, 97, 25, 38, 15, 129, 82, 35, 91, 89, 87, 72, 34, 26, 132, 127, 112, 78, 77, 73, 64, 47, 46, 42, 33, 29, 21, 138, 137, 136, 135, 131, 128, 116, 113, 111, 104, 103, 98, 92, 84, 81, 70, 69, 67, 65, 49, 45, 31, 24, 20, 17, 10] },
	{ "s": "MOST", "p": [78, 81, 67, 64, 135, 129, 116, 111, 72, 54, 30, 136, 113, 112, 103, 94, 91, 89, 88, 87, 84, 73, 66, 33, 31, 4] },
	{ "s": "MOSTLY", "p": [129] },
	{ "s": "MOTHER", "p": [78] },
	{ "s": "MOTHER/INFANT", "p": [78] },
	{ "s": "MOTOR", "p": [78, 64] },
	{ "s": "MOUSE", "p": [86, 137, 82, 74, 111, 91, 75, 73, 72] },
	{ "s": "MOVE", "p": [75, 86, 137, 82, 73, 76, 72, 84, 83, 78, 77, 74, 63, 62, 61, 60, 59, 58, 57] },
	{ "s": "MOVED", "p": [138, 81, 83, 75, 73] },
	{ "s": "MOVEMENT", "p": [81] },
	{ "s": "MOVES", "p": [73] },
	{ "s": "MOVING", "p": [82, 113, 89, 76] },
	{ "s": "MOZILLA", "p": [84] },
	{ "s": "MSC", "p": [77, 83, 136] },
	{ "s": "MSC-1", "p": [77] },
	{ "s": "MSC-1-AS-X", "p": [77] },
	{ "s": "MSCCPV1", "p": [89] },
	{ "s": "MSCS", "p": [83, 77] },
	{ "s": "MTU", "p": [78] },
	{ "s": "MUCH", "p": [64, 87, 81, 76, 12] },
	{ "s": "MULTI", "p": [89, 137, 78, 67] },
	{ "s": "MULTI-HOMED", "p": [89] },
	{ "s": "MULTI-PART", "p": [67] },
	{ "s": "MULTI-PROTOCOL", "p": [78] },
	{ "s": "MULTI-SELECT", "p": [137] },
	{ "s": "MULTIPLE", "p": [118, 135, 77, 29, 137, 78, 89, 28, 67, 117, 65, 57, 56, 136, 131, 116, 113, 101, 100, 98, 96, 86, 84, 82, 81, 73, 72, 25, 5, 4] },
	{ "s": "MULTIPLES", "p": [75] },
	{ "s": "MULTIPLIED", "p": [64] },
	{ "s": "MULTIPLY", "p": [64, 62] },
	{ "s": "MULTIPLYING", "p": [61, 123] },
	{ "s": "MUSCLE", "p": [78] },
	{ "s": "MUSCLES", "p": [78] },
	{ "s": "MUST", "p": [135, 89, 84, 65, 21, 4, 131, 78, 76, 67, 66, 64, 53, 29, 25, 11, 8] },
	{ "s": "MXGRAPH", "p": [84] },
	{ "s": "MXRESOURCES", "p": [84] },
	{ "s": "MY", "p": [35, 137, 50] }
]